screwhashesset/README.MD
screwhashesset/__init__.py
screwhashesset/requirements.txt
screwhashesset/thirdparty.json
screwhashesset-0.12.dist-info/LICENSE.rst
screwhashesset-0.12.dist-info/METADATA
screwhashesset-0.12.dist-info/WHEEL
screwhashesset-0.12.dist-info/top_level.txt
screwhashesset-0.12.dist-info/RECORD
