Metadata-Version: 2.1
Name: screwhashesset
Version: 0.12
Summary: A set that handles all kinds of objects (hashable or not) and preserves the order of the elements
Home-page: https://github.com/hansalemaos/screwhashesset
Author: Johannes Fischer
Author-email: aulasparticularesdealemaosp@gmail.com
License: MIT
Keywords: set,hash,collections
Classifier: Development Status :: 4 - Beta
Classifier: Programming Language :: Python :: 3 :: Only
Classifier: Programming Language :: Python :: 3.10
Classifier: Topic :: Software Development :: Libraries :: Python Modules
Classifier: Topic :: Utilities
License-File: LICENSE.rst
